<resources>
<!--This Slovak translation is licenced under www.creativecommons.org/licenses/by-nc-nd/3.0/deed.en by MIUI CZ&SK www.miuios.cz-->
    <string name="label_airplane_mode">Lietadlo</string>
    <string name="label_silent_mode">Tichý režim</string>
    <string name="label_reboot">Reštart</string>
    <string name="label_shutdown">Vypnúť</string>
    <string name="label_alert_reboot">Reštart</string>
    <string name="label_alert_shutdown">Vypnúť</string>
    <string name="label_blank">Späť</string>
    <string name="label_emergency_call">Núdzový hovor</string>
    <string name="label_alert_recovery">Recovery</string>
    <string name="label_alert_fastboot">Fastboot</string>    
</resources>
